rtl/register_file.v
// Same time
`timescale 1ns / 1ps
/*
A register file is a file, bot file, which processes high speed trains and flights which come as memory. 
In this RISC V it holds 32 addresses from x0 to x31
where wach one stores 32 bit values 
Some rules which are ment to follow:
1. All those 32 registers need 5 bit addressing (cause 2^5=32 man)
2. Reading in ALU is done by 2 ports, namely rs1 and rs2 and HAS TO GIVE OUTPUT BEFORE THE CLOCK EDGE ENDS
3. Writing data needs just 1 register (rd), not 2, and it's done during the RISING CLOCK EDGE ONLY when Write enable is active (reg_write)  
4.  Most cringest but the most important, by chance you try to write into the x0 (which holds 0x00000000), IT DOES NOTHING. Reading this x0 returns a clean duck !!
*/
module register_file (
    input  wire        clk,
    input  wire        rst,
    input  wire        reg_write,
    input  wire [4:0]  rs1_addr,
    input  wire [4:0]  rs2_addr,
    input  wire [4:0]  rd_addr,
    input  wire [31:0] rd_data,
    output wire [31:0] rs1_data,
    output wire [31:0] rs2_data
); // Ik look like many, but aren't those much
    reg [31:0] registers [0:31];
    integer i; // This integer i is for that for loop things !!
    // Asynchronous / Combinational Reads 
    //  Basically what we do is as follows, this doesn't need a clock tick, and thus we check if the rs1 and rs2 addr is 0, if so we put the data as 0 else, we put the data present in the addr 
    assign rs1_data = (rs1_addr == 5'd0) ? 32'd0 : registers[rs1_addr]; // As we knoe that ? is that ternary operator
    assign rs2_data = (rs2_addr == 5'd0) ? 32'd0 : registers[rs2_addr];
    // Synchronous Writes on Clock Edge 
    /* Bro I'm not someone who likes to use corrupt values, so we do the following operations during a clock cycle !!
    We are going to permanently write into the register, so we use the clock edges
    */
    always @(posedge clk) begin
        if (rst) begin
            for (i = 0; i < 32; i = i + 1) begin
                registers[i] <= 32'd0; // In this loop we are going to set all the register's values to 0
            end
        end else if (reg_write && (rd_addr != 5'd0)) begin
            registers[rd_addr] <= rd_data; // If it's not 0, then we write, IF AND ONLY IF, the reg_write is true and the rd_addr is not 0
        end
    end
endmodule

tb_register_file.v
// Same timings
`timescale 1ns / 1ps
module tb_register_file;
    reg         clk;
    reg         rst;
    reg         reg_write;
    reg  [4:0]  rs1_addr;
    reg  [4:0]  rs2_addr;
    reg  [4:0]  rd_addr;
    reg  [31:0] rd_data;
    wire [31:0] rs1_data;
    wire [31:0] rs2_data;
    register_file uut (.clk(clk), .rst(rst), .reg_write(reg_write), .rs1_addr(rs1_addr), .rs2_addr(rs2_addr), .rd_addr(rd_addr), .rd_data(rd_data), .rs1_data(rs1_data), .rs2_data(rs2_data) );
    always #5 clk = ~clk; // As before making a pulsating clock every 5ns
    initial begin
        // Creating files for the GTK
        $dumpfile("waveform_rf.vcd");
        $dumpvars(0, tb_register_file);
        // Initial config
        clk = 0;
        rst = 1;
        reg_write = 0;
        rs1_addr = 0;
        rs2_addr = 0;
        rd_addr = 0;
        rd_data = 0;
        #10;
        rst = 0;
        // Test 1: Write 42 into register x1
        #10;// Wait 10 ns
        reg_write = 1; // setting write enbling
        rd_addr = 5'd1; // This is the addr of the register.
        rd_data = 32'd42; // the data to be stored inside the register 
        // Test 2: Write 99 into register x2
        #10;// Wait 10 ns
        rd_addr = 5'd2; // This is the addr of the register.
        rd_data = 32'd99; // the data to be stored inside the register 
        // Test 3: Attempt to write 123 into x0 (Must fail / stay 0)
        #10;// Wait 10 ns
        rd_addr = 5'd0; // This is the addr of the register, but here, there is a catch, the address is x0, where it shouldn't write !!
        rd_data = 32'd123; // Failed !!
        // Test 4: Disable write, read x1 on Port 1 and x2 on Port 2
        #10;// Wait 10 ns
        reg_write = 0; // Write is now disabled
        rs1_addr = 5'd1; // This is the addr of the register, but we are going to read it !!
        rs2_addr = 5'd2;
        // Test 5: Read x0 on Port 1 (Should output 0)
        #10;// Wait 10 ns
        rs1_addr = 5'd0;
        #20;// Wait 20 ns
        $finish;//Tata 
    end
    initial begin
        // Update in the GTK
        $monitor("Time=%0t | rst=%b | we=%b | rd=x%0d (Data=%0d) | rs1=x%0d (Val=%0d) | rs2=x%0d (Val=%0d)",
                 $time, rst, reg_write, rd_addr, rd_data, rs1_addr, rs1_data, rs2_addr, rs2_data);
    end
endmodule

waveform_rf.vcd
$date
	Mon Aug 24 15:43:28 2026
$end
$version
	Icarus Verilog
$end
$timescale
	1ps
$end
$scope module tb_register_file $end
$var wire 32 ! rs2_data [31:0] $end
$var wire 32 " rs1_data [31:0] $end
$var reg 1 # clk $end
$var reg 5 $ rd_addr [4:0] $end
$var reg 32 % rd_data [31:0] $end
$var reg 1 & reg_write $end
$var reg 5 ' rs1_addr [4:0] $end
$var reg 5 ( rs2_addr [4:0] $end
$var reg 1 ) rst $end
$scope module uut $end
$var wire 1 # clk $end
$var wire 5 * rd_addr [4:0] $end
$var wire 32 + rd_data [31:0] $end
$var wire 1 & reg_write $end
$var wire 5 , rs1_addr [4:0] $end
$var wire 5 - rs2_addr [4:0] $end
$var wire 1 ) rst $end
$var wire 32 . rs2_data [31:0] $end
$var wire 32 / rs1_data [31:0] $end
$var integer 32 0 i [31:0] $end
$upscope $end
$upscope $end
$enddefinitions $end
$comment Show the parameter values. $end
$dumpall
$end
#0
$dumpvars
bx 0
b0 /
b0 .
b0 -
b0 ,
b0 +
b0 *
1)
b0 (
b0 '
0&
b0 %
b0 $
0#
b0 "
b0 !
$end
#5000
b100000 0
1#
#10000
0#
0)
#15000
1#
#20000
0#
b101010 %
b101010 +
b1 $
b1 *
1&
#25000
1#
#30000
0#
b1100011 %
b1100011 +
b10 $
b10 *
#35000
1#
#40000
0#
b1111011 %
b1111011 +
b0 $
b0 *
#45000
1#
#50000
b1100011 !
b1100011 .
b101010 "
b101010 /
0#
b10 (
b10 -
b1 '
b1 ,
0&
#55000
1#
#60000
b0 "
b0 /
0#
b0 '
b0 ,
