rtl/data_memory.v
// Same time
`timescale 1ns / 1ps
// Hardware module for single-cycle RV32I Data Memory
module data_memory (
    input  wire        clk,        // Clock signal for synchronous write operations
    input  wire        rst,        // Active high reset to clear memory contents
    input  wire        mem_write,  // Write enable control signal for store instructions
    input  wire        mem_read,   // Read enable control signal for load instructions
    input  wire [31:0] addr,       // 32-bit memory address calculated by ALU
    input  wire [31:0] write_data, // 32-bit data to store into memory from rs2
    output wire [31:0] read_data   // 32-bit data loaded from memory to destination register
);
    // Declare internal RAM array of 64 words each 32 bits wide
    reg [31:0] memory [0:63];
    // Integer loop variable for reset initialization
    integer i;
    // Asynchronous read logic returning word when read enable is high
    assign read_data = (mem_read) ? memory[addr[31:2]] : 32'd0;
    // Synchronous write block triggering on rising clock edge
    always @(posedge clk) begin
        // Check if synchronous reset is active
        if (rst) begin
            // Iterate through all 64 memory locations
            for (i = 0; i < 64; i = i + 1) begin
                // Clear memory location to zero
                memory[i] <= 32'd0;
            end
        // Write data if write enable is active
        end else if (mem_write) begin
            // Store 32-bit word using upper address bits as word index
            memory[addr[31:2]] <= write_data;
        end
    end
endmodule

tb/tb_data_memory.v
// same time
`timescale 1ns / 1ps
// Testbench module for verifying Data Memory operations
module tb_data_memory;
    // Testbench register driving clock signal
    reg        clk;
    // Testbench register driving reset signal
    reg        rst;
    // Testbench register driving memory write enable
    reg        mem_write;
    // Testbench register driving memory read enable
    reg        mem_read;
    // Testbench register driving memory address
    reg  [31:0] addr;
    // Testbench register driving data to be written
    reg  [31:0] write_data;
    // Testbench wire capturing loaded data output
    wire [31:0] read_data;
    // Unit under test instantiation
    data_memory uut (
        // Connect clock port
        .clk(clk),
        // Connect reset port
        .rst(rst),
        // Connect write enable port
        .mem_write(mem_write),
        // Connect read enable port
        .mem_read(mem_read),
        // Connect address port
        .addr(addr),
        // Connect write data port
        .write_data(write_data),
        // Connect read data port
        .read_data(read_data)
    );
    // Generate continuous clock pulse every 5ns
    always #5 clk = ~clk;
    // Stimulus initial block
    initial begin
        // Configure waveform dump file for GTKWave
        $dumpfile("waveform_dm.vcd");
        // Dump all testbench variables
        $dumpvars(0, tb_data_memory);
        // Initialize control signals
        clk = 0;
        rst = 1;
        mem_write = 0;
        mem_read = 0;
        addr = 32'd0;
        write_data = 32'd0;
        // Wait 10ns for reset to take effect
        #10;
        // Release reset
        rst = 0;
        // Test 1: Store word 0xDEADBEEF at byte address 0 (word index 0)
        #10;
        mem_write = 1;
        mem_read = 0;
        addr = 32'd0;
        write_data = 32'hDEADBEEF;
        // Test 2: Store word 0x12345678 at byte address 4 (word index 1)
        #10;
        addr = 32'd4;
        write_data = 32'h12345678;
        // Test 3: Disable write and read back data from byte address 0
        #10;
        mem_write = 0;
        mem_read = 1;
        addr = 32'd0;
        // Test 4: Read back data from byte address 4
        #10;
        addr = 32'd4;
        // Test 5: Disable read enable to verify output zeroes out
        #10;
        mem_read = 0;
        // Finish simulation
        #10;
        $finish;
    end
    // Monitor block for terminal logging
    initial begin
        // Display memory activity across time steps
        $monitor("Time=%0t | rst=%b | we=%b | re=%b | Addr=0x%h | WData=0x%h | RData=0x%h",
                 $time, rst, mem_write, mem_read, addr, write_data, read_data);
    end
endmodule

waveform_dm.vcd
$date
	Mon Aug 24 15:43:29 2026
$end
$version
	Icarus Verilog
$end
$timescale
	1ps
$end
$scope module tb_data_memory $end
$var wire 32 ! read_data [31:0] $end
$var reg 32 " addr [31:0] $end
$var reg 1 # clk $end
$var reg 1 $ mem_read $end
$var reg 1 % mem_write $end
$var reg 1 & rst $end
$var reg 32 ' write_data [31:0] $end
$scope module uut $end
$var wire 32 ( addr [31:0] $end
$var wire 1 # clk $end
$var wire 1 $ mem_read $end
$var wire 1 % mem_write $end
$var wire 1 & rst $end
$var wire 32 ) write_data [31:0] $end
$var wire 32 * read_data [31:0] $end
$var integer 32 + i [31:0] $end
$upscope $end
$upscope $end
$enddefinitions $end
$comment Show the parameter values. $end
$dumpall
$end
#0
$dumpvars
bx +
b0 *
b0 )
b0 (
b0 '
1&
0%
0$
0#
b0 "
b0 !
$end
#5000
b1000000 +
1#
#10000
0#
0&
#15000
1#
#20000
0#
b11011110101011011011111011101111 '
b11011110101011011011111011101111 )
1%
#25000
1#
#30000
0#
b10010001101000101011001111000 '
b10010001101000101011001111000 )
b100 "
b100 (
#35000
1#
#40000
b11011110101011011011111011101111 !
b11011110101011011011111011101111 *
0#
b0 "
b0 (
1$
0%
#45000
1#
#50000
b10010001101000101011001111000 !
b10010001101000101011001111000 *
0#
b100 "
b100 (
#55000
1#
#60000
b0 !
b0 *
0#
0$
