program_counter.v
/* this is the basics of the code
This is also called as a configurtor instruction, and not for physical design 
the syntax of this timescale is `timescale <Reference_Time> / <Time_Precision>
*/
`timescale 1ns / 1ps
//since I'm working on verilog for the first time, I'm going to use soo many comments for understanding the code and it's structutre
//every code has to start with the folllowing codes, module <module_name>(<parameters>); <contents> endmodule
module program_counter (input  wire clk, input  wire rst, input wire [31:0] pc_next, output reg [31:0] pc );
    //After the defination of the module is done, we will have to write the conditions and all for what this is working 
    // Update the Program Counter on every rising edge of the clock
    //always means, whatever happens run it every time.It's syntax being, always @ (@ means at event) (<condition of event)> begin <statements> end 
    always @(posedge clk) begin // posedge = register updates after the clock rises from low to high 
        //the if else condition works in the following syntax
        /* 
        if (<condition>) begin  
            <statement>
        end else if (<condition>) begin 
            <statement>
        end else if (<condition>) begin
            <statement>
        end */
        if (rst) begin //rst is reset pin
            pc <= 32'h00000000; // When it's true, we reset PC to address 0
        end else begin
            pc <= pc_next;      // When it's false, we update PC to the next address. Next address = Current PC address + 4 bytes. BUT <= is not normal assignation, but it's caled non-blocking assignment,
            // non-blocking assignment means that the assignment happens at the same clock cycle and not in the next clock cycle, it does the following
            /* if the following code is there
            A <= B
            C <= A 
            then it means to the computer:
            Do not update anything yet. Just look at the current values. Ready? Okay, simultaneously push B into A, and push the old value of A into C.
            */
        end
    end // Rule of thumb: Always use <= when you are inside an always @(posedge clk) block.
endmodule

tb_program_counter.v
/* The first code is called the physical design code, and this code, is called testbench
A testbench is a set of specified codes which acts as a virtual lab for the hardware, and it's testing the circuit in the computer instead of real hardware
This helps us understand what we do irl while in software, so that if there is any misfiring, we can correct it right away !!
A testbench is strictly for simulation
*/
`timescale 1ns / 1ps
//here we redefine the created module for the refrences, but in different format
/* module name
decleration
assingation 
initilization of the testbench
endmodule
*/
module tb_program_counter;
    reg clk; // a reg is shortform for register, all the clock reset and all those, which are in the always stuff, need to be for sure in this reg only, and now wire
    reg rst; 
    wire [31:0] pc_next; // wire is simply a transport for the output to a place, any assign or any output must be in this wire only
    wire [31:0] pc;
    //now we configure this testbench to that of the actual code 
    program_counter uut ( .clk(clk), .rst(rst), .pc_next(pc_next), .pc(pc) );// uut means unit under test, this way it will know that we are testing for this one 
    //here we assign the initial stuff like clock and the next address 
    assign pc_next = pc + 32'd4; //Since RSIC-V is 32 bit long, it has to just 4 bytes (32 bits) every time for a new instruction
    always #5 clk = ~clk; // #5 means with for 5 nanoseconds (nanoseconds cause, we defined it as 1ns), and every 5ns shift the pulse 
    // This is the begining of the test benck.
    initial begin //twist ye hai ki, always runs every time the code is on, but initial runs exactly ONCE 
        //bhai these are the special names to tell our Mr. Icarus Verilog to record all the signals and save them in that waveform.vcd file. That .vcd file is for GTKWave sir to read later 
        $dumpfile("waveform.vcd"); 
        $dumpvars(0, tb_program_counter);
        clk = 0;//set clock to 0
        rst = 1;//set reset to 1
        #15; //wait for 15ns 
        rst = 0;//afater 15ns set reset to 0
        #80;//wait 80ns
        rst = 1; // after 80ns set reset to 1
        #10;//wait 10ns
        rst = 0; //after 10ns again reset reset to 0
        #20;//last and final 20 ns of the program
        $finish; //katam, over it's stops
    end
    initial begin
        $monitor("Time=%0t | rst=%b | pc=%h | pc_next=%h", $time, rst, pc, pc_next);// same as printf in C and cout in C++ and print in python 
    end
endmodule

waveform.vcd
$date
	Fri Aug 21 14:50:56 2026
$end
$version
	Icarus Verilog
$end
$timescale
	1ps
$end
$scope module tb_program_counter $end
$var wire 32 ! pc_next [31:0] $end
$var wire 32 " pc [31:0] $end
$var reg 1 # clk $end
$var reg 1 $ rst $end
$scope module uut $end
$var wire 1 # clk $end
$var wire 32 % pc_next [31:0] $end
$var wire 1 $ rst $end
$var reg 32 & pc [31:0] $end
$upscope $end
$upscope $end
$enddefinitions $end
$comment Show the parameter values. $end
$dumpall
$end
#0
$dumpvars
bx &
bx %
1$
0#
bx "
bx !
$end
#5000
b100 !
b100 %
b0 "
b0 &
1#
#10000
0#
#15000
b1000 !
b1000 %
b100 "
b100 &
1#
0$
#20000
0#
#25000
b1100 !
b1100 %
b1000 "
b1000 &
1#
#30000
0#
#35000
b10000 !
b10000 %
b1100 "
b1100 &
1#
#40000
0#
#45000
b10100 !
b10100 %
b10000 "
b10000 &
1#
#50000
0#
#55000
b11000 !
b11000 %
b10100 "
b10100 &
1#
#60000
0#
#65000
b11100 !
b11100 %
b11000 "
b11000 &
1#
#70000
0#
#75000
b100000 !
b100000 %
b11100 "
b11100 &
1#
#80000
0#
#85000
b100100 !
b100100 %
b100000 "
b100000 &
1#
#90000
0#
#95000
b100 !
b100 %
b0 "
b0 &
1#
1$
#100000
0#
#105000
b1000 !
b1000 %
b100 "
b100 &
1#
0$
#110000
0#
#115000
b1100 !
b1100 %
b1000 "
b1000 &
1#
#120000
0#
#125000
b10000 !
b10000 %
b1100 "
b1100 &
1#
