alu.v
// Same
`timescale 1ns / 1ps
// Hardware module for the RV32I Arithmetic Logic Unit
module alu (
    input  wire [31:0] a,           // First 32-bit operand coming from rs1 register
    input  wire [31:0] b,           // Second 32-bit operand coming from rs2 or immediate generator
    input  wire [3:0]  alu_control, // 4-bit control code deciding which operation to perform
    output reg  [31:0] result,      // 32-bit calculation output
    output wire        zero         // 1-bit active-high flag that turns 1 when result is exactly 0
);
    // Operation code constant for addition
    localparam ALU_ADD  = 4'b0000;
    // Operation code constant for subtraction
    localparam ALU_SUB  = 4'b0001;
    // Operation code constant for bitwise AND
    localparam ALU_AND  = 4'b0010;
    // Operation code constant for bitwise OR
    localparam ALU_OR   = 4'b0011;
    // Operation code constant for bitwise XOR
    localparam ALU_XOR  = 4'b0100;
    // Operation code constant for shift left logical
    localparam ALU_SLL  = 4'b0101;
    // Operation code constant for shift right logical
    localparam ALU_SRL  = 4'b0110;
    // Operation code constant for shift right arithmetic with sign preservation
    localparam ALU_SRA  = 4'b0111;
    // Operation code constant for signed set less than comparison
    localparam ALU_SLT  = 4'b1000;
    // Operation code constant for unsigned set less than comparison
    localparam ALU_SLTU = 4'b1001;
    // Combinational evaluation block that triggers on any input change
    always @(*) begin
        // Multiplexer logic switching based on the 4-bit control signal
        case (alu_control)
            // Add operand a and operand b
            ALU_ADD:  result = a + b;
            // Subtract operand b from operand a
            ALU_SUB:  result = a - b;
            // Perform bitwise AND between a and b
            ALU_AND:  result = a & b;
            // Perform bitwise OR between a and b
            ALU_OR:   result = a | b;
            // Perform bitwise XOR between a and b
            ALU_XOR:  result = a ^ b;
            // Shift operand a left by the lower 5 bits of operand b
            ALU_SLL:  result = a << b[4:0];
            // Shift operand a right logically by the lower 5 bits of operand b
            ALU_SRL:  result = a >> b[4:0];
            // Shift operand a right arithmetically preserving sign bit
            ALU_SRA:  result = $signed(a) >>> b[4:0];
            // Signed comparison: output 1 if a is less than b, otherwise 0
            ALU_SLT:  result = ($signed(a) < $signed(b)) ? 32'd1 : 32'd0;
            // Unsigned comparison: output 1 if magnitude of a is less than b, otherwise 0
            ALU_SLTU: result = (a < b) ? 32'd1 : 32'd0;
            // Default fallback value for safety to avoid latch inference
            default:  result = 32'd0;
        // Close the case switch block
        endcase
    end
    // Combinational assign setting zero flag to 1 if result equals 0, else 0
    assign zero = (result == 32'd0) ? 1'b1 : 1'b0;
endmodule

tb_alu.v
// Same time
`timescale 1ns / 1ps
// Testbench module for verifying ALU operations
module tb_alu;
    // 32-bit register signal to drive operand A
    reg  [31:0] a;
    // 32-bit register signal to drive operand B
    reg  [31:0] b;
    // 4-bit register signal to drive ALU operation selector
    reg  [3:0]  alu_control;
    // 32-bit wire to capture the calculated ALU output
    wire [31:0] result;
    // 1-bit wire to capture the zero flag status
    wire        zero;
    // Signed wire declaration to display negative integers cleanly in decimal
    wire signed [31:0] signed_result;
    // Continuous assignment connecting unsigned wire to signed wire
    assign signed_result = result;
    // Instantiation of the ALU module under test
    alu uut (
        // Hook up testbench operand a to module input a
        .a(a),
        // Hook up testbench operand b to module input b
        .b(b),
        // Hook up testbench control code to module input alu_control
        .alu_control(alu_control),
        // Hook up module result output to testbench wire result
        .result(result),
        // Hook up module zero output to testbench wire zero
        .zero(zero)
    );
    // Initial procedural block containing simulation stimulus sequence
    initial begin
        // Configure VCD dump file name for GTKWave
        $dumpfile("waveform_alu.vcd");
        // Dump all signals in this testbench scope
        $dumpvars(0, tb_alu);
        // Test 1: Test addition with 15 + 10 = 25
        a = 32'd15;
        b = 32'd10;
        alu_control = 4'b0000;
        // Wait 10 simulation time units
        #10;
        // Test 2: Test subtraction with equal values 20 - 20 = 0 to trigger zero flag
        a = 32'd20;
        b = 32'd20;
        alu_control = 4'b0001;
        // Wait 10 simulation time units
        #10;
        // Test 3: Test bitwise AND with hex masks
        a = 32'h0000000F;
        b = 32'h00000007;
        alu_control = 4'b0010;
        // Wait 10 simulation time units
        #10;
        // Test 4: Test bitwise OR with hex values
        a = 32'h000000F0;
        b = 32'h0000000F;
        alu_control = 4'b0011;
        // Wait 10 simulation time units
        #10;
        // Test 5: Test shift left logical by shifting 1 left by 3 bits
        a = 32'd1;
        b = 32'd3;
        alu_control = 4'b0101;
        // Wait 10 simulation time units
        #10;
        // Test 6: Test arithmetic right shift preserving negative sign on -16 shifted by 2
        a = -32'd16;
        b = 32'd2;
        alu_control = 4'b0111;
        // Wait 10 simulation time units
        #10;
        // Test 7: Test signed set less than where -10 is less than 5
        a = -32'd10;
        b = 32'd5;
        alu_control = 4'b1000;
        // Wait 10 simulation time units
        #10;
        // Test 8: Test unsigned set less than where negative bit pattern evaluates as large unsigned magnitude
        a = -32'd10;
        b = 32'd5;
        alu_control = 4'b1001;
        // Wait 10 simulation time units
        #10;
        // Terminate the simulation
        $finish;
    end
    // Initial block for logging console output during simulation run
    initial begin
        // Print header and variable values whenever monitored signals change
        $monitor("Time=%0t | Ctrl=%b | A=%0d (0x%h) | B=%0d (0x%h) | Result=%0d (0x%h) | Zero=%b",
                 $time, alu_control, a, a, b, b, signed_result, result, zero);
    end
endmodule

waveform_alu.vcd
$date
	Mon Aug 24 13:35:48 2026
$end
$version
	Icarus Verilog
$end
$timescale
	1ps
$end
$scope module tb_alu $end
$var wire 32 ! signed_result [31:0] $end
$var wire 1 " zero $end
$var wire 32 # result [31:0] $end
$var reg 32 $ a [31:0] $end
$var reg 4 % alu_control [3:0] $end
$var reg 32 & b [31:0] $end
$scope module uut $end
$var wire 32 ' a [31:0] $end
$var wire 4 ( alu_control [3:0] $end
$var wire 32 ) b [31:0] $end
$var wire 1 " zero $end
$var parameter 4 * ALU_ADD $end
$var parameter 4 + ALU_AND $end
$var parameter 4 , ALU_OR $end
$var parameter 4 - ALU_SLL $end
$var parameter 4 . ALU_SLT $end
$var parameter 4 / ALU_SLTU $end
$var parameter 4 0 ALU_SRA $end
$var parameter 4 1 ALU_SRL $end
$var parameter 4 2 ALU_SUB $end
$var parameter 4 3 ALU_XOR $end
$var reg 32 4 result [31:0] $end
$upscope $end
$upscope $end
$enddefinitions $end
$comment Show the parameter values. $end
$dumpall
b100 3
b1 2
b110 1
b111 0
b1001 /
b1000 .
b101 -
b11 ,
b10 +
b0 *
$end
#0
$dumpvars
b11001 4
b1010 )
b0 (
b1111 '
b1010 &
b0 %
b1111 $
b11001 #
0"
b11001 !
$end
#10000
1"
b0 !
b0 #
b0 4
b1 %
b1 (
b10100 &
b10100 )
b10100 $
b10100 '
#20000
0"
b111 !
b111 #
b111 4
b10 %
b10 (
b111 &
b111 )
b1111 $
b1111 '
#30000
b11111111 !
b11111111 #
b11111111 4
b11 %
b11 (
b1111 &
b1111 )
b11110000 $
b11110000 '
#40000
b1000 !
b1000 #
b1000 4
b101 %
b101 (
b11 &
b11 )
b1 $
b1 '
#50000
b11111111111111111111111111111100 !
b11111111111111111111111111111100 #
b11111111111111111111111111111100 4
b111 %
b111 (
b10 &
b10 )
b11111111111111111111111111110000 $
b11111111111111111111111111110000 '
#60000
b1 !
b1 #
b1 4
b1000 %
b1000 (
b101 &
b101 )
b11111111111111111111111111110110 $
b11111111111111111111111111110110 '
#70000
1"
b0 !
b0 #
b0 4
b1001 %
b1001 (
